argparse_utils/__init__.py
argparse_utils/datetime.py
argparse_utils/json.py
argparse_utils/mapping.py
argparse_utils/python_literal.py
argparse_utils/store_mapped_action.py
argparse_utils-1.3.0.dist-info/LICENSE
argparse_utils-1.3.0.dist-info/METADATA
argparse_utils-1.3.0.dist-info/WHEEL
argparse_utils-1.3.0.dist-info/top_level.txt
argparse_utils-1.3.0.dist-info/RECORD
