Metadata-Version: 2.1
Name: argparse-utils
Version: 1.3.0
Summary: A collection of utilities for the Python standard-library argparse module
Home-page: https://github.com/madman-bob/python-argparse-utils
Author: Robert Wright
Author-email: madman.bob@hotmail.co.uk
License: MIT
Platform: UNKNOWN
Classifier: License :: OSI Approved :: MIT License
Classifier: Programming Language :: Python :: 3
Classifier: Programming Language :: Python :: 3.5
Classifier: Programming Language :: Python :: 3.6
Classifier: Programming Language :: Python :: 3.7
Classifier: Programming Language :: Python :: 3.8
Requires-Python: >=3.5
Requires-Dist: twine
